{
  "1": {
    "inputs": {
      "ckpt_name": "bluePencilXL_v700.safetensors"
    },
    "class_type": "CheckpointLoaderSimple"
  },
  "2": {
    "inputs": {
      "control_net_name": "controlnet-scribble-sdxl-1.0.safetensors"
    },
    "class_type": "ControlNetLoader"
  },
  "3": {
    "inputs": {
      "width": 200,
      "height": 200,
      "red": 255,
      "green": 255,
      "blue": 255
    },
    "class_type": "Image Blank"
  },
  "4": {
    "inputs": {
      "width": 512,
      "height": 512,
      "batch_size": 1
    },
    "class_type": "EmptyLatentImage"
  },
  "5": {
    "inputs": {
      "text": "花",
      "font_size": 80,
      "font": "meiryoub.ttc",
      "fill_color_hex": "#000000",
      "stroke_color_hex": "#000000",
      "stroke_thickness": 0,
      "padding": 0,
      "horizontal_alignment": "center",
      "vertical_alignment": "middle",
      "x_shift": 0,
      "y_shift": -20,
      "image": ["3", 0]
    },
    "class_type": "Text Overlay"
  },
  "6": {
    "inputs": {
      "from_translate": "auto",
      "to_translate": "english",
      "add_proxies": false,
      "proxies": "",
      "auth_data": "",
      "service": "GoogleTranslator",
      "text": "樱花",
      "Show proxy": "proxy_hide",
      "Show authorization": "authorization_hide",
      "clip": ["1", 1]
    },
    "class_type": "DeepTranslatorCLIPTextEncodeNode"
  },
  "7": {
    "inputs": {
      "from_translate": "auto",
      "to_translate": "english",
      "add_proxies": false,
      "proxies": "",
      "auth_data": "",
      "service": "GoogleTranslator",
      "text": "低品质",
      "Show proxy": "proxy_hide",
      "Show authorization": "authorization_hide",
      "clip": ["1", 1]
    },
    "class_type": "DeepTranslatorCLIPTextEncodeNode"
  },
  "8": {
    "inputs": {
      "strength": 1,
      "start_percent": 0,
      "end_percent": 1,
      "positive": ["6", 0],
      "negative": ["7", 0],
      "control_net": ["2", 0],
      "image": ["5", 0]
    },
    "class_type": "ControlNetApplyAdvanced"
  },
  "9": {
    "inputs": {
      "seed": 123456789,
      "steps": 20,
      "cfg": 7,
      "sampler_name": "ddim",
      "scheduler": "ddim_uniform",
      "denoise": 1,
      "model": ["1", 0],
      "positive": ["8", 0],
      "negative": ["8", 1],
      "latent_image": ["4", 0]
    },
    "class_type": "KSampler"
  },
  "10": {
    "inputs": {
      "samples": ["9", 0],
      "vae": ["1", 2]
    },
    "class_type": "VAEDecode"
  },
  "11": {
    "inputs": {
      "filename_prefix": "ComfyUI",
      "file_type": "JPEG",
      "remove_metadata": false,
      "images": ["10", 0]
    },
    "class_type": "SaveImagePlus"
  }
}